[
  {
    "id": 0,
    "position": {
      "x": 12.242626599888702,
      "y": 1500.0
    },
    "estimated_position": {
      "x": 467.9379879344233,
      "y": 0.0
    }
  },
  {
    "id": 1,
    "position": {
      "x": 1999.9999999999998,
      "y": 1395.224518888097
    },
    "estimated_position": {
      "x": 7014.054704181436,
      "y": 528.3128388775658
    }
  },
  {
    "id": 2,
    "position": {
      "x": 1892.0422927100722,
      "y": 2.2737367544323206e-13
    },
    "estimated_position": {
      "x": 6634.375737139327,
      "y": 5033.171622189335
    }
  },
  {
    "id": 3,
    "position": {
      "x": 0.0,
      "y": 31.004989308624545
    },
    "estimated_position": {
      "x": 0.0,
      "y": 4924.044197375994
    }
  }
]